{
    "file_path": "./data\\包头-招10.pdf.json",
    "data": {
        "0": [
            {
                "地址": [
                    {
                        "text": "包头市",
                        "start": 0,
                        "end": 3,
                        "probability": 0.5749583898311812
                    }
                ]
            }
        ],
        "1": [
            {
                "公司": [
                    {
                        "text": "内蒙古招标有限责任公司",
                        "start": 89,
                        "end": 100,
                        "probability": 0.8864615433046374
                    }
                ],
                "组织": [
                    {
                        "text": "包头市市政工程管理局",
                        "start": 71,
                        "end": 81,
                        "probability": 0.8801587106201367
                    },
                    {
                        "text": "内蒙古招标有限责任公司",
                        "start": 89,
                        "end": 100,
                        "probability": 0.9013681528337258
                    }
                ]
            }
        ],
        "2": [
            {
                "组织": [
                    {
                        "text": "评标委员会",
                        "start": 3782,
                        "end": 3787,
                        "probability": 0.5005002193669839
                    }
                ]
            }
        ],
        "3": [
            {
                "组织": [
                    {
                        "text": "评标委员会",
                        "start": 1101,
                        "end": 1106,
                        "probability": 0.6077421610550289
                    }
                ]
            }
        ],
        "4": [
            {}
        ],
        "5": [
            {}
        ],
        "6": [
            {}
        ],
        "7": [
            {
                "组织": [
                    {
                        "text": "包头市发展和改革委员会",
                        "start": 290,
                        "end": 301,
                        "probability": 0.7033092865335391
                    },
                    {
                        "text": "包头市发展和改革委员会",
                        "start": 111,
                        "end": 122,
                        "probability": 0.838661548477873
                    },
                    {
                        "text": "包头市发展和改革\n委员会",
                        "start": 141,
                        "end": 153,
                        "probability": 0.8791136571985021
                    },
                    {
                        "text": "包头市市政工程管理局",
                        "start": 93,
                        "end": 103,
                        "probability": 0.8828446120526934
                    }
                ],
                "地址": [
                    {
                        "text": "包头市九原区",
                        "start": 276,
                        "end": 282,
                        "probability": 0.28876801790623574
                    },
                    {
                        "text": "九原区太原路（沙\n河街--新春街）",
                        "start": 521,
                        "end": 538,
                        "probability": 0.4185332029656834
                    }
                ]
            }
        ],
        "8": [
            {
                "地址": [
                    {
                        "text": "包头市公共资源交易大厅三楼",
                        "start": 267,
                        "end": 280,
                        "probability": 0.4296799253851269
                    }
                ]
            }
        ],
        "9": [
            {
                "公司": [
                    {
                        "text": "内蒙古招标\n有限责任公司",
                        "start": 86,
                        "end": 98,
                        "probability": 0.8380380351488448
                    }
                ],
                "组织": [
                    {
                        "text": "包头市市政工程管理局",
                        "start": 102,
                        "end": 112,
                        "probability": 0.9122781316079909
                    },
                    {
                        "text": "包头市公共资\n源交易中心",
                        "start": 42,
                        "end": 54,
                        "probability": 0.7723778057500184
                    },
                    {
                        "text": "包头市公共资源交易网",
                        "start": 5,
                        "end": 15,
                        "probability": 0.6422852021651124
                    },
                    {
                        "text": "包头市市政工程管理局",
                        "start": 68,
                        "end": 78,
                        "probability": 0.9237346203720094
                    },
                    {
                        "text": "内蒙古招标\n有限责任公司",
                        "start": 86,
                        "end": 98,
                        "probability": 0.9430491215645453
                    }
                ],
                "地址": [
                    {
                        "text": "包头市稀土高新区黄河大街 86\n号时代广场C 座907 室",
                        "start": 116,
                        "end": 145,
                        "probability": 0.43031946402365406
                    }
                ],
                "姓名": [
                    {
                        "text": "田文",
                        "start": 170,
                        "end": 172,
                        "probability": 0.40481866207622375
                    }
                ],
                "电话": [
                    {
                        "text": "15044961696",
                        "start": 199,
                        "end": 210,
                        "probability": 0.5214365423200888
                    },
                    {
                        "text": "0472-5175533",
                        "start": 183,
                        "end": 195,
                        "probability": 0.3736930061132391
                    }
                ]
            }
        ],
        "10": [
            {
                "公司": [
                    {
                        "text": "内蒙古招标有限责任公司",
                        "start": 132,
                        "end": 143,
                        "probability": 0.49797553524039273
                    }
                ],
                "组织": [
                    {
                        "text": "转龙液酒厂",
                        "start": 427,
                        "end": 432,
                        "probability": 0.440543762658109
                    },
                    {
                        "text": "包头市市政工程管理局",
                        "start": 69,
                        "end": 79,
                        "probability": 0.9383741917613406
                    },
                    {
                        "text": "内蒙古招标有限责任公司",
                        "start": 132,
                        "end": 143,
                        "probability": 0.8274552378709288
                    },
                    {
                        "text": "转龙液酒厂",
                        "start": 322,
                        "end": 327,
                        "probability": 0.316806823611401
                    }
                ],
                "地址": [
                    {
                        "text": "内蒙古包头市劳动路81号",
                        "start": 83,
                        "end": 95,
                        "probability": 0.6014121986500669
                    }
                ],
                "姓名": [
                    {
                        "text": "田文",
                        "start": 110,
                        "end": 112,
                        "probability": 0.4719897716559558
                    }
                ],
                "电话": [
                    {
                        "text": "0472-5175533",
                        "start": 116,
                        "end": 128,
                        "probability": 0.6558744155812235
                    }
                ]
            }
        ],
        "11": [
            {
                "组织": [
                    {
                        "text": "最高人民法院",
                        "start": 435,
                        "end": 441,
                        "probability": 0.4642960421333697
                    }
                ]
            }
        ],
        "12": [
            {}
        ],
        "13": [
            {}
        ],
        "14": [
            {
                "组织": [
                    {
                        "text": "包头市公共资源交易中心",
                        "start": 470,
                        "end": 481,
                        "probability": 0.36276922828129443
                    }
                ]
            }
        ],
        "15": [
            {
                "组织": [
                    {
                        "text": "包头市公共资源交易中心",
                        "start": 308,
                        "end": 319,
                        "probability": 0.8008479401375297
                    }
                ],
                "地址": [
                    {
                        "text": "里市检察院北侧",
                        "start": 0,
                        "end": 7,
                        "probability": 0.5659695506889406
                    }
                ]
            }
        ],
        "16": [
            {
                "组织": [
                    {
                        "text": "国家发展改革委",
                        "start": 136,
                        "end": 143,
                        "probability": 0.875829293578068
                    }
                ]
            }
        ],
        "17": [
            {
                "姓名": [
                    {
                        "text": "李强",
                        "start": 164,
                        "end": 166,
                        "probability": 0.7547107207450665
                    }
                ],
                "电话": [
                    {
                        "text": "0472-6862119",
                        "start": 174,
                        "end": 186,
                        "probability": 0.9135158069688707
                    }
                ]
            }
        ],
        "18": [
            {}
        ],
        "19": [
            {
                "组织": [
                    {
                        "text": "评标委员会",
                        "start": 698,
                        "end": 703,
                        "probability": 0.4409632460310604
                    }
                ]
            }
        ],
        "20": [
            {}
        ],
        "21": [
            {
                "组织": [
                    {
                        "text": "评标委员会",
                        "start": 735,
                        "end": 740,
                        "probability": 0.3963042352806454
                    }
                ]
            }
        ],
        "22": [
            {}
        ],
        "23": [
            {}
        ],
        "24": [
            {}
        ],
        "25": [
            {}
        ],
        "26": [
            {
                "组织": [
                    {
                        "text": "评标委员会",
                        "start": 191,
                        "end": 196,
                        "probability": 0.47555019607996485
                    },
                    {
                        "text": "评标委员会",
                        "start": 124,
                        "end": 129,
                        "probability": 0.42484063460932475
                    }
                ]
            }
        ],
        "27": [
            {}
        ],
        "28": [
            {}
        ],
        "29": [
            {}
        ],
        "30": [
            {}
        ],
        "31": [
            {}
        ],
        "32": [
            {}
        ],
        "33": [
            {}
        ],
        "34": [
            {
                "组织": [
                    {
                        "text": "评标委员会",
                        "start": 596,
                        "end": 601,
                        "probability": 0.4087050044478495
                    }
                ]
            }
        ],
        "35": [
            {
                "组织": [
                    {
                        "text": "评标委员会",
                        "start": 893,
                        "end": 898,
                        "probability": 0.2839785894352076
                    }
                ]
            }
        ],
        "36": [
            {
                "组织": [
                    {
                        "text": "评标委员会",
                        "start": 530,
                        "end": 535,
                        "probability": 0.6075449598493812
                    }
                ]
            }
        ],
        "37": [
            {
                "组织": [
                    {
                        "text": "评标委员会",
                        "start": 135,
                        "end": 140,
                        "probability": 0.43252154309811885
                    }
                ]
            }
        ],
        "38": [
            {}
        ],
        "39": [
            {}
        ],
        "40": [
            {
                "组织": [
                    {
                        "text": "清标委员",
                        "start": 139,
                        "end": 143,
                        "probability": 0.34397909805900895
                    }
                ]
            }
        ],
        "41": [
            {}
        ],
        "42": [
            {
                "组织": [
                    {
                        "text": "住 房 城 乡 建 设 部",
                        "start": 0,
                        "end": 13,
                        "probability": 0.9760799762466021
                    },
                    {
                        "text": "国家工商行政管理总局",
                        "start": 17,
                        "end": 27,
                        "probability": 0.9727779510233603
                    }
                ]
            }
        ],
        "43": [
            {
                "组织": [
                    {
                        "text": "住房\n城乡建设部",
                        "start": 91,
                        "end": 99,
                        "probability": 0.9741066275871617
                    },
                    {
                        "text": "国家工商行政管理总局",
                        "start": 100,
                        "end": 110,
                        "probability": 0.9739329794202618
                    }
                ]
            }
        ],
        "44": [
            {}
        ],
        "45": [
            {
                "组织": [
                    {
                        "text": "评标委员会",
                        "start": 4074,
                        "end": 4079,
                        "probability": 0.5972906388893229
                    }
                ]
            }
        ],
        "46": [
            {
                "组织": [
                    {
                        "text": "评标委员会",
                        "start": 947,
                        "end": 952,
                        "probability": 0.37032048910985793
                    }
                ]
            }
        ],
        "47": [
            {}
        ],
        "48": [
            {}
        ],
        "49": [
            {}
        ],
        "50": [
            {}
        ],
        "51": [
            {
                "组织": [
                    {
                        "text": "争议评审小组",
                        "start": 4137,
                        "end": 4143,
                        "probability": 0.43286732307059594
                    }
                ]
            }
        ],
        "52": [
            {
                "组织": [
                    {
                        "text": "争议评审小组",
                        "start": 7,
                        "end": 13,
                        "probability": 0.4440790478761869
                    }
                ]
            }
        ],
        "53": [
            {
                "公司": [
                    {
                        "text": "包头市市政工程管理局",
                        "start": 1496,
                        "end": 1506,
                        "probability": 0.3211215072887299
                    }
                ],
                "组织": [
                    {
                        "text": "包头市市政工程管理局",
                        "start": 1496,
                        "end": 1506,
                        "probability": 0.8244550039857224
                    }
                ]
            }
        ],
        "54": [
            {}
        ],
        "55": [
            {}
        ],
        "56": [
            {
                "组织": [
                    {
                        "text": "包头市市政工程管理局",
                        "start": 260,
                        "end": 270,
                        "probability": 0.9133655790620843
                    }
                ],
                "地址": [
                    {
                        "text": "包头市市政工程管理局",
                        "start": 260,
                        "end": 270,
                        "probability": 0.39505289902164975
                    }
                ]
            }
        ],
        "57": [
            {
                "地址": [
                    {
                        "text": "包头市稀土高新区劳动路81号",
                        "start": 153,
                        "end": 167,
                        "probability": 0.7532230925429424
                    }
                ],
                "电话": [
                    {
                        "text": "0472-5175533",
                        "start": 224,
                        "end": 236,
                        "probability": 0.772048999209602
                    }
                ]
            }
        ],
        "58": [
            {}
        ],
        "59": [
            {}
        ],
        "60": [
            {}
        ],
        "61": [
            {}
        ],
        "62": [
            {}
        ],
        "63": [
            {}
        ],
        "64": [
            {}
        ],
        "65": [
            {}
        ],
        "66": [
            {}
        ],
        "67": [
            {}
        ],
        "68": [
            {}
        ],
        "69": [
            {}
        ],
        "70": [
            {}
        ],
        "71": [
            {}
        ],
        "72": [
            {}
        ],
        "73": [
            {}
        ],
        "74": [
            {}
        ],
        "75": [
            {}
        ],
        "76": [
            {}
        ],
        "77": [
            {}
        ],
        "78": [
            {}
        ],
        "79": [
            {}
        ],
        "80": [
            {}
        ],
        "81": [
            {}
        ],
        "82": [
            {
                "组织": [
                    {
                        "text": "联合体",
                        "start": 60,
                        "end": 63,
                        "probability": 0.4340385593688936
                    },
                    {
                        "text": "联合体",
                        "start": 50,
                        "end": 53,
                        "probability": 0.5189379728924521
                    }
                ]
            }
        ],
        "83": [
            {}
        ],
        "84": [
            {}
        ],
        "85": [
            {}
        ],
        "86": [
            {}
        ],
        "87": [
            {}
        ],
        "88": [
            {}
        ],
        "89": [
            {}
        ],
        "90": [
            {}
        ],
        "91": [
            {}
        ],
        "92": [
            {}
        ],
        "93": [
            {}
        ],
        "94": [
            {}
        ],
        "95": [
            {}
        ],
        "96": [
            {}
        ],
        "97": [
            {}
        ],
        "98": [
            {}
        ],
        "99": [
            {}
        ],
        "100": [
            {}
        ],
        "101": [
            {}
        ],
        "102": [
            {}
        ],
        "103": [
            {}
        ],
        "104": [
            {}
        ],
        "105": [
            {}
        ],
        "106": [
            {}
        ],
        "107": [
            {}
        ],
        "108": [
            {}
        ],
        "109": [
            {}
        ],
        "110": [
            {}
        ],
        "111": [
            {}
        ],
        "112": [
            {}
        ],
        "113": [
            {}
        ],
        "114": [
            {}
        ],
        "115": [
            {}
        ],
        "116": [
            {}
        ],
        "117": [
            {}
        ],
        "118": [
            {}
        ],
        "119": [
            {}
        ],
        "120": [
            {}
        ],
        "121": [
            {}
        ],
        "122": [
            {}
        ],
        "123": [
            {}
        ],
        "124": [
            {}
        ],
        "125": [
            {}
        ],
        "126": [
            {
                "组织": [
                    {
                        "text": "中国人民银行",
                        "start": 383,
                        "end": 389,
                        "probability": 0.8934127558713953
                    }
                ]
            }
        ],
        "127": [
            {}
        ],
        "128": [
            {}
        ],
        "129": [
            {}
        ],
        "130": [
            {
                "组织": [
                    {
                        "text": "中国人民银行",
                        "start": 243,
                        "end": 249,
                        "probability": 0.4616165902138327
                    }
                ]
            }
        ],
        "131": [
            {}
        ],
        "132": [
            {
                "组织": [
                    {
                        "text": "投料试车",
                        "start": 507,
                        "end": 511,
                        "probability": 0.41226462581012413
                    }
                ]
            }
        ],
        "133": [
            {}
        ],
        "134": [
            {}
        ],
        "135": [
            {}
        ],
        "136": [
            {
                "组织": [
                    {
                        "text": "中国人民银行",
                        "start": 171,
                        "end": 177,
                        "probability": 0.3133516785705268
                    },
                    {
                        "text": "中国人民银行",
                        "start": 132,
                        "end": 138,
                        "probability": 0.7434129960845226
                    }
                ]
            }
        ],
        "137": [
            {
                "组织": [
                    {
                        "text": "中国人民银行",
                        "start": 406,
                        "end": 412,
                        "probability": 0.8629506605600312
                    },
                    {
                        "text": "中\n国人民银行",
                        "start": 445,
                        "end": 452,
                        "probability": 0.3142187608933611
                    }
                ]
            }
        ],
        "138": [
            {}
        ],
        "139": [
            {}
        ],
        "140": [
            {
                "组织": [
                    {
                        "text": "中国人民银行",
                        "start": 352,
                        "end": 358,
                        "probability": 0.821271622748899
                    }
                ]
            }
        ],
        "141": [
            {}
        ],
        "142": [
            {}
        ],
        "143": [
            {}
        ],
        "144": [
            {}
        ],
        "145": [
            {}
        ],
        "146": [
            {}
        ],
        "147": [
            {}
        ],
        "148": [
            {}
        ],
        "149": [
            {}
        ],
        "150": [
            {}
        ],
        "151": [
            {}
        ],
        "152": [
            {}
        ],
        "153": [
            {}
        ],
        "154": [
            {}
        ],
        "155": [
            {}
        ],
        "156": [
            {
                "组织": [
                    {
                        "text": "仲裁委员会",
                        "start": 344,
                        "end": 349,
                        "probability": 0.31746962453655314
                    },
                    {
                        "text": "争议评审小组",
                        "start": 7,
                        "end": 13,
                        "probability": 0.3612000650171012
                    },
                    {
                        "text": "争\n议评审小组",
                        "start": 43,
                        "end": 50,
                        "probability": 0.42613988902166966
                    }
                ]
            }
        ],
        "157": [
            {}
        ],
        "158": [
            {}
        ],
        "159": [
            {
                "组织": [
                    {
                        "text": "包头市市政工程管理局",
                        "start": 367,
                        "end": 377,
                        "probability": 0.9098080386118212
                    }
                ],
                "地址": [
                    {
                        "text": "包头市市政工程管理局",
                        "start": 367,
                        "end": 377,
                        "probability": 0.5448237773504339
                    }
                ]
            }
        ],
        "160": [
            {}
        ],
        "161": [
            {}
        ],
        "162": [
            {}
        ],
        "163": [
            {}
        ],
        "164": [
            {}
        ],
        "165": [
            {}
        ],
        "166": [
            {}
        ],
        "167": [
            {}
        ],
        "168": [
            {}
        ],
        "169": [
            {}
        ],
        "170": [
            {}
        ],
        "171": [
            {
                "地址": [
                    {
                        "text": "包头市",
                        "start": 21,
                        "end": 24,
                        "probability": 0.35158961470231986
                    }
                ]
            }
        ],
        "172": [
            {}
        ],
        "173": [
            {}
        ],
        "174": [
            {}
        ],
        "175": [
            {}
        ],
        "176": [
            {}
        ],
        "177": [
            {}
        ],
        "178": [
            {}
        ],
        "179": [
            {}
        ],
        "180": [
            {}
        ],
        "181": [
            {}
        ],
        "182": [
            {}
        ],
        "183": [
            {}
        ],
        "184": [
            {}
        ],
        "185": [
            {
                "组织": [
                    {
                        "text": "包头 仲裁委员会",
                        "start": 64,
                        "end": 72,
                        "probability": 0.9697364185908057
                    },
                    {
                        "text": "包头市 人民法院",
                        "start": 83,
                        "end": 91,
                        "probability": 0.8459264252845209
                    }
                ]
            }
        ],
        "186": [
            {}
        ],
        "187": [
            {}
        ],
        "188": [
            {}
        ],
        "189": [
            {
                "公司": [
                    {
                        "text": "包头市市政工程管理局",
                        "start": 8,
                        "end": 18,
                        "probability": 0.358662830113019
                    }
                ],
                "组织": [
                    {
                        "text": "包头市市政工程管理局",
                        "start": 8,
                        "end": 18,
                        "probability": 0.9597054180006523
                    }
                ]
            }
        ],
        "190": [
            {}
        ],
        "191": [
            {
                "地址": [
                    {
                        "text": "包头市稀土高新区劳动路81号",
                        "start": 95,
                        "end": 109,
                        "probability": 0.8627613484827208
                    }
                ],
                "电话": [
                    {
                        "text": "0472-5175533",
                        "start": 163,
                        "end": 175,
                        "probability": 0.8565434189577559
                    }
                ]
            }
        ],
        "192": [
            {}
        ],
        "193": [
            {}
        ],
        "194": [
            {}
        ],
        "195": [
            {}
        ],
        "196": [
            {}
        ],
        "197": [
            {}
        ],
        "198": [
            {}
        ],
        "199": [
            {}
        ],
        "200": [
            {}
        ],
        "201": [
            {}
        ],
        "202": [
            {}
        ],
        "203": [
            {}
        ],
        "204": [
            {}
        ],
        "205": [
            {}
        ],
        "206": [
            {}
        ],
        "207": [
            {}
        ],
        "208": [
            {}
        ],
        "209": [
            {}
        ],
        "210": [
            {}
        ],
        "211": [
            {}
        ],
        "212": [
            {}
        ],
        "213": [
            {
                "地址": [
                    {
                        "text": "包头市九原区",
                        "start": 49,
                        "end": 55,
                        "probability": 0.513519757731487
                    }
                ]
            }
        ],
        "214": [
            {}
        ],
        "215": [
            {}
        ],
        "216": [
            {}
        ],
        "217": [
            {}
        ],
        "218": [
            {}
        ],
        "219": [
            {
                "电话": [
                    {
                        "text": "传真",
                        "start": 8,
                        "end": 10,
                        "probability": 0.6428079305149126
                    }
                ]
            }
        ],
        "220": [
            {}
        ],
        "221": [
            {}
        ],
        "222": [
            {}
        ],
        "223": [
            {}
        ],
        "224": [
            {}
        ],
        "225": [
            {}
        ],
        "226": [
            {}
        ],
        "227": [
            {}
        ],
        "228": [
            {}
        ],
        "229": [
            {}
        ],
        "230": [
            {}
        ],
        "231": [
            {}
        ],
        "232": [
            {}
        ],
        "233": [
            {}
        ],
        "234": [
            {}
        ],
        "235": [
            {}
        ],
        "236": [
            {}
        ],
        "237": [
            {}
        ],
        "238": [
            {}
        ],
        "239": [
            {}
        ],
        "240": [
            {}
        ]
    }
}